Metadata-Version: 2.0
Name: django-github-webhook27
Version: 0.1.1.2
Summary: Django view for GitHub webhook recievers, forked to work on 2.7
Home-page: https://github.com/andrewgross/django-github-webhook
Author: Andrew Gross
Author-email: andrewwgross@gmail.com
License: BSD
Keywords: django,view,github,webhook,signature
Platform: UNKNOWN
Classifier: Development Status :: 5 - Production/Stable
Classifier: Intended Audience :: Developers
Classifier: License :: OSI Approved :: BSD License
Classifier: Programming Language :: Python
Classifier: Programming Language :: Python :: 3
Classifier: Programming Language :: Python :: 3.4
Classifier: Programming Language :: Python :: 3.5
Classifier: Programming Language :: Python :: Implementation :: CPython
Classifier: Programming Language :: Python :: Implementation :: PyPy
Classifier: Topic :: Utilities
Requires-Dist: Django
